{
  "gitSyncId": "68f95f221126eb768730abe4_bc5e7176-c705-4da7-a799-8d9eb3601cc4",
  "id": "Pedidos_getPedidosPorCobrar",
  "pluginId": "postgres-plugin",
  "pluginType": "DB",
  "unpublishedAction": {
    "actionConfiguration": {
      "body": "SELECT\n    c.nombre AS customer_name,\n    COUNT(p.id) AS order_count\nFROM\n    pedidos p\nJOIN\n    clientes c ON p.cliente_id = c.id\nWHERE\n    p.estado_id = 9 -- ID 9 = 'entregado'\nGROUP BY\n    c.nombre\nORDER BY\n    order_count DESC;",
      "encodeParamsToggle": true,
      "paginationType": "NONE",
      "pluginSpecifiedTemplates": [
        {
          "value": true
        }
      ],
      "timeoutInMillisecond": 10000
    },
    "confirmBeforeExecute": false,
    "datasource": {
      "id": "Prox_Pedidos",
      "isAutoGenerated": false,
      "name": "Prox_Pedidos",
      "pluginId": "postgres-plugin"
    },
    "dynamicBindingPathList": [],
    "name": "getPedidosPorCobrar",
    "pageId": "Pedidos",
    "runBehaviour": "ON_PAGE_LOAD",
    "userSetOnLoad": true
  }
}