{
  "gitSyncId": "68f95f221126eb768730abe4_be897a20-40f0-4789-b726-ca31b394ca66",
  "id": "Indicadores_utils.obtenerNombreSubdepto",
  "pluginId": "js-plugin",
  "pluginType": "JS",
  "unpublishedAction": {
    "actionConfiguration": {
      "encodeParamsToggle": true,
      "jsArguments": [
        {
          "name": "id"
        },
        {
          "name": "subdeptosData",
          "value": "{{getSubdepartamentos.data}}"
        }
      ],
      "paginationType": "NONE",
      "timeoutInMillisecond": 10000
    },
    "collectionId": "Indicadores_utils",
    "confirmBeforeExecute": false,
    "datasource": {
      "isAutoGenerated": false,
      "name": "UNUSED_DATASOURCE",
      "pluginId": "js-plugin"
    },
    "dynamicBindingPathList": [
      {
        "key": "body"
      }
    ],
    "fullyQualifiedName": "utils.obtenerNombreSubdepto",
    "name": "obtenerNombreSubdepto",
    "pageId": "Indicadores",
    "runBehaviour": "MANUAL",
    "userSetOnLoad": false
  }
}