{
  "gitSyncId": "68f95f221126eb768730abe4_4d341735-2fd6-4924-a066-ab93976a7e9c",
  "id": "Indicadores_utils.obtenerNombreColaborador",
  "pluginId": "js-plugin",
  "pluginType": "JS",
  "unpublishedAction": {
    "actionConfiguration": {
      "encodeParamsToggle": true,
      "jsArguments": [
        {
          "name": "id"
        },
        {
          "name": "colaboradoresData",
          "value": "{{getColaboradores.data}}"
        }
      ],
      "paginationType": "NONE",
      "timeoutInMillisecond": 10000
    },
    "collectionId": "Indicadores_utils",
    "confirmBeforeExecute": false,
    "datasource": {
      "isAutoGenerated": false,
      "name": "UNUSED_DATASOURCE",
      "pluginId": "js-plugin"
    },
    "dynamicBindingPathList": [
      {
        "key": "body"
      }
    ],
    "fullyQualifiedName": "utils.obtenerNombreColaborador",
    "name": "obtenerNombreColaborador",
    "pageId": "Indicadores",
    "runBehaviour": "MANUAL",
    "userSetOnLoad": false
  }
}