{
  "gitSyncId": "68f95f221126eb768730abe4_cac22830-5f8e-48b2-a20f-cdf5f995a82f",
  "id": "Pedidos Copy_getPedidosParaCharts",
  "pluginId": "postgres-plugin",
  "pluginType": "DB",
  "unpublishedAction": {
    "actionConfiguration": {
      "body": "SELECT \n    p.fecha_plazo,\n    me.estado_interno,\n    me.orden_visual\nFROM \n    pedidos p\nJOIN \n    maestro_estados me ON p.estado_id = me.id\nWHERE \n    -- Excluye los IDs de estado 10 (Finalizado) y 11 (Cancelado)\n    p.estado_id NOT IN (10, 11)",
      "encodeParamsToggle": true,
      "paginationType": "NONE",
      "pluginSpecifiedTemplates": [
        {
          "value": true
        }
      ],
      "timeoutInMillisecond": 10000
    },
    "confirmBeforeExecute": false,
    "datasource": {
      "id": "Prox_Pedidos",
      "isAutoGenerated": false,
      "name": "Prox_Pedidos",
      "pluginId": "postgres-plugin"
    },
    "dynamicBindingPathList": [],
    "name": "getPedidosParaCharts",
    "pageId": "Pedidos Copy",
    "runBehaviour": "ON_PAGE_LOAD",
    "userSetOnLoad": true
  }
}